{
  "values": {
    "falloutmc:nuka_cola": {
      "addiction": false,
      "deceaseChance": 0,
      "deceaseEffects": [
        "falloutmc:example_effect"
      ],
      "effects": [
        {
          "duration": 0,
          "effect": "falloutmc:example_effect"
        }
      ],
      "hpRestore": 0,
      "hungerRestore": 0,
      "plantable": false,
      "radiation": 10,
      "recipe": false,
      "thirstRestore": 0,
      "value": 10,
      "weight": 1.0
    },
    "minecraft:apple": {
      "addiction": false,
      "deceaseChance": 0,
      "deceaseEffects": [
        "falloutmc:example_effect"
      ],
      "effects": [
        {
          "duration": 0,
          "effect": "falloutmc:example_effect"
        }
      ],
      "hpRestore": 3,
      "hungerRestore": 10,
      "plantable": true,
      "radiation": 5,
      "recipe": false,
      "thirstRestore": 2,
      "value": 5,
      "weight": 0.2
    },
    "minecraft:baked_potato": {
      "addiction": false,
      "deceaseChance": 0,
      "deceaseEffects": [
        "falloutmc:example_effect"
      ],
      "effects": [
        {
          "duration": 0,
          "effect": "falloutmc:example_effect"
        }
      ],
      "hpRestore": 5,
      "hungerRestore": 15,
      "plantable": false,
      "radiation": 8,
      "recipe": true,
      "thirstRestore": 3,
      "value": 6,
      "weight": 0.4
    },
    "minecraft:beef": {
      "addiction": false,
      "deceaseChance": 0,
      "deceaseEffects": [
        "falloutmc:example_effect"
      ],
      "effects": [
        {
          "duration": 0,
          "effect": "falloutmc:example_effect"
        }
      ],
      "hpRestore": 6,
      "hungerRestore": 12,
      "plantable": false,
      "radiation": 15,
      "recipe": false,
      "thirstRestore": 2,
      "value": 8,
      "weight": 0.5
    },
    "minecraft:beetroot": {
      "addiction": false,
      "deceaseChance": 0,
      "deceaseEffects": [
        "falloutmc:example_effect"
      ],
      "effects": [
        {
          "duration": 0,
          "effect": "falloutmc:example_effect"
        }
      ],
      "hpRestore": 6,
      "hungerRestore": 5,
      "plantable": true,
      "radiation": 3,
      "recipe": false,
      "thirstRestore": 1,
      "value": 2,
      "weight": 0.3
    },
    "minecraft:bread": {
      "addiction": false,
      "deceaseChance": 0,
      "deceaseEffects": [
        "falloutmc:example_effect"
      ],
      "effects": [
        {
          "duration": 0,
          "effect": "falloutmc:example_effect"
        }
      ],
      "hpRestore": 8,
      "hungerRestore": 7,
      "plantable": false,
      "radiation": 5,
      "recipe": true,
      "thirstRestore": 0,
      "value": 5,
      "weight": 0.4
    },
    "minecraft:cake": {
      "addiction": false,
      "deceaseChance": 0,
      "deceaseEffects": [
        "falloutmc:example_effect"
      ],
      "effects": [
        {
          "duration": 0,
          "effect": "falloutmc:example_effect"
        }
      ],
      "hpRestore": 7,
      "hungerRestore": 18,
      "plantable": false,
      "radiation": 8,
      "recipe": true,
      "thirstRestore": 5,
      "value": 12,
      "weight": 0.7
    },
    "minecraft:carrot": {
      "addiction": false,
      "deceaseChance": 0,
      "deceaseEffects": [
        "falloutmc:example_effect"
      ],
      "effects": [
        {
          "duration": 0,
          "effect": "falloutmc:example_effect"
        }
      ],
      "hpRestore": 2,
      "hungerRestore": 5,
      "plantable": true,
      "radiation": 2,
      "recipe": false,
      "thirstRestore": 1,
      "value": 2,
      "weight": 0.3
    },
    "minecraft:chicken": {
      "addiction": false,
      "deceaseChance": 0,
      "deceaseEffects": [
        "falloutmc:example_effect"
      ],
      "effects": [
        {
          "duration": 0,
          "effect": "falloutmc:example_effect"
        }
      ],
      "hpRestore": 3,
      "hungerRestore": 6,
      "plantable": false,
      "radiation": 4,
      "recipe": false,
      "thirstRestore": 1,
      "value": 2,
      "weight": 0.4
    },
    "minecraft:chorus_fruit": {
      "addiction": false,
      "deceaseChance": 0,
      "deceaseEffects": [
        "falloutmc:example_effect"
      ],
      "effects": [
        {
          "duration": 0,
          "effect": "falloutmc:example_effect"
        }
      ],
      "hpRestore": 10,
      "hungerRestore": 20,
      "plantable": false,
      "radiation": 10,
      "recipe": false,
      "thirstRestore": 20,
      "value": 33,
      "weight": 0.4
    },
    "minecraft:cod": {
      "addiction": false,
      "deceaseChance": 0,
      "deceaseEffects": [
        "falloutmc:example_effect"
      ],
      "effects": [
        {
          "duration": 0,
          "effect": "falloutmc:example_effect"
        }
      ],
      "hpRestore": 6,
      "hungerRestore": 6,
      "plantable": false,
      "radiation": 6,
      "recipe": false,
      "thirstRestore": 2,
      "value": 4,
      "weight": 0.5
    },
    "minecraft:cooked_beef": {
      "addiction": false,
      "deceaseChance": 0,
      "deceaseEffects": [
        "falloutmc:example_effect"
      ],
      "effects": [
        {
          "duration": 0,
          "effect": "falloutmc:example_effect"
        }
      ],
      "hpRestore": 6,
      "hungerRestore": 15,
      "plantable": false,
      "radiation": 8,
      "recipe": false,
      "thirstRestore": 1,
      "value": 15,
      "weight": 0.6
    },
    "minecraft:cooked_chicken": {
      "addiction": false,
      "deceaseChance": 0,
      "deceaseEffects": [
        "falloutmc:example_effect"
      ],
      "effects": [
        {
          "duration": 0,
          "effect": "falloutmc:example_effect"
        }
      ],
      "hpRestore": 6,
      "hungerRestore": 17,
      "plantable": false,
      "radiation": 5,
      "recipe": false,
      "thirstRestore": 2,
      "value": 15,
      "weight": 0.5
    },
    "minecraft:cooked_cod": {
      "addiction": false,
      "deceaseChance": 0,
      "deceaseEffects": [
        "falloutmc:example_effect"
      ],
      "effects": [
        {
          "duration": 0,
          "effect": "falloutmc:example_effect"
        }
      ],
      "hpRestore": 8,
      "hungerRestore": 12,
      "plantable": false,
      "radiation": 5,
      "recipe": false,
      "thirstRestore": 1,
      "value": 15,
      "weight": 0.4
    },
    "minecraft:cooked_mutton": {
      "addiction": false,
      "deceaseChance": 0,
      "deceaseEffects": [
        "falloutmc:example_effect"
      ],
      "effects": [
        {
          "duration": 0,
          "effect": "falloutmc:example_effect"
        }
      ],
      "hpRestore": 7,
      "hungerRestore": 13,
      "plantable": false,
      "radiation": 9,
      "recipe": false,
      "thirstRestore": 1,
      "value": 15,
      "weight": 0.5
    },
    "minecraft:cooked_porkchop": {
      "addiction": false,
      "deceaseChance": 0,
      "deceaseEffects": [
        "falloutmc:example_effect"
      ],
      "effects": [
        {
          "duration": 0,
          "effect": "falloutmc:example_effect"
        }
      ],
      "hpRestore": 6,
      "hungerRestore": 12,
      "plantable": false,
      "radiation": 10,
      "recipe": false,
      "thirstRestore": 1,
      "value": 15,
      "weight": 0.6
    },
    "minecraft:cooked_rabbit": {
      "addiction": false,
      "deceaseChance": 0,
      "deceaseEffects": [
        "falloutmc:example_effect"
      ],
      "effects": [
        {
          "duration": 0,
          "effect": "falloutmc:example_effect"
        }
      ],
      "hpRestore": 8,
      "hungerRestore": 10,
      "plantable": false,
      "radiation": 3,
      "recipe": false,
      "thirstRestore": 2,
      "value": 15,
      "weight": 0.5
    },
    "minecraft:cooked_salmon": {
      "addiction": false,
      "deceaseChance": 0,
      "deceaseEffects": [
        "falloutmc:example_effect"
      ],
      "effects": [
        {
          "duration": 0,
          "effect": "falloutmc:example_effect"
        }
      ],
      "hpRestore": 5,
      "hungerRestore": 14,
      "plantable": false,
      "radiation": 2,
      "recipe": false,
      "thirstRestore": 1,
      "value": 15,
      "weight": 0.4
    },
    "minecraft:cookie": {
      "addiction": false,
      "deceaseChance": 0,
      "deceaseEffects": [
        "falloutmc:example_effect"
      ],
      "effects": [
        {
          "duration": 0,
          "effect": "falloutmc:example_effect"
        }
      ],
      "hpRestore": 7,
      "hungerRestore": 5,
      "plantable": false,
      "radiation": 4,
      "recipe": false,
      "thirstRestore": 0,
      "value": 12,
      "weight": 0.15
    },
    "minecraft:dried_kelp": {
      "addiction": false,
      "deceaseChance": 0,
      "deceaseEffects": [
        "falloutmc:example_effect"
      ],
      "effects": [
        {
          "duration": 0,
          "effect": "falloutmc:example_effect"
        }
      ],
      "hpRestore": 4,
      "hungerRestore": 8,
      "plantable": false,
      "radiation": 14,
      "recipe": false,
      "thirstRestore": 0,
      "value": 4,
      "weight": 0.1
    },
    "minecraft:enchanted_golden_apple": {
      "addiction": false,
      "deceaseChance": 0,
      "deceaseEffects": [
        "falloutmc:example_effect"
      ],
      "effects": [
        {
          "duration": 0,
          "effect": "falloutmc:example_effect"
        }
      ],
      "hpRestore": 30,
      "hungerRestore": 30,
      "plantable": false,
      "radiation": 0,
      "recipe": false,
      "thirstRestore": 30,
      "value": 100,
      "weight": 3.0
    },
    "minecraft:glow_berries": {
      "addiction": false,
      "deceaseChance": 0,
      "deceaseEffects": [
        "falloutmc:example_effect"
      ],
      "effects": [
        {
          "duration": 0,
          "effect": "falloutmc:example_effect"
        }
      ],
      "hpRestore": 4,
      "hungerRestore": 6,
      "plantable": false,
      "radiation": 16,
      "recipe": false,
      "thirstRestore": 4,
      "value": 5,
      "weight": 0.2
    },
    "minecraft:golden_apple": {
      "addiction": false,
      "deceaseChance": 0,
      "deceaseEffects": [
        "falloutmc:example_effect"
      ],
      "effects": [
        {
          "duration": 0,
          "effect": "falloutmc:example_effect"
        }
      ],
      "hpRestore": 19,
      "hungerRestore": 12,
      "plantable": false,
      "radiation": 2,
      "recipe": false,
      "thirstRestore": 14,
      "value": 50,
      "weight": 2.0
    },
    "minecraft:golden_carrot": {
      "addiction": false,
      "deceaseChance": 0,
      "deceaseEffects": [
        "falloutmc:example_effect"
      ],
      "effects": [
        {
          "duration": 0,
          "effect": "falloutmc:example_effect"
        }
      ],
      "hpRestore": 15,
      "hungerRestore": 11,
      "plantable": false,
      "radiation": 2,
      "recipe": false,
      "thirstRestore": 3,
      "value": 33,
      "weight": 0.5
    },
    "minecraft:honey_bottle": {
      "addiction": false,
      "deceaseChance": 0,
      "deceaseEffects": [
        "falloutmc:example_effect"
      ],
      "effects": [
        {
          "duration": 0,
          "effect": "falloutmc:example_effect"
        }
      ],
      "hpRestore": 3,
      "hungerRestore": 12,
      "plantable": false,
      "radiation": 7,
      "recipe": false,
      "thirstRestore": 3,
      "value": 12,
      "weight": 0.5
    },
    "minecraft:lingering_potion": {
      "addiction": false,
      "deceaseChance": 0,
      "deceaseEffects": [
        "falloutmc:example_effect"
      ],
      "effects": [
        {
          "duration": 0,
          "effect": "falloutmc:example_effect"
        }
      ],
      "hpRestore": 0,
      "hungerRestore": 0,
      "plantable": false,
      "radiation": 20,
      "recipe": false,
      "thirstRestore": 12,
      "value": 0,
      "weight": 1.0
    },
    "minecraft:melon_slice": {
      "addiction": false,
      "deceaseChance": 0,
      "deceaseEffects": [
        "falloutmc:example_effect"
      ],
      "effects": [
        {
          "duration": 0,
          "effect": "falloutmc:example_effect"
        }
      ],
      "hpRestore": 2,
      "hungerRestore": 4,
      "plantable": false,
      "radiation": 3,
      "recipe": false,
      "thirstRestore": 15,
      "value": 2,
      "weight": 0.25
    },
    "minecraft:milk_bucket": {
      "addiction": false,
      "deceaseChance": 0,
      "deceaseEffects": [
        "falloutmc:example_effect"
      ],
      "effects": [
        {
          "duration": 0,
          "effect": "falloutmc:example_effect"
        }
      ],
      "hpRestore": 6,
      "hungerRestore": 2,
      "plantable": false,
      "radiation": 4,
      "recipe": false,
      "thirstRestore": 20,
      "value": 6,
      "weight": 1.0
    },
    "minecraft:mutton": {
      "addiction": false,
      "deceaseChance": 0,
      "deceaseEffects": [
        "falloutmc:example_effect"
      ],
      "effects": [
        {
          "duration": 0,
          "effect": "falloutmc:example_effect"
        }
      ],
      "hpRestore": 6,
      "hungerRestore": 11,
      "plantable": false,
      "radiation": 11,
      "recipe": false,
      "thirstRestore": 1,
      "value": 5,
      "weight": 0.5
    },
    "minecraft:poisonous_potato": {
      "addiction": false,
      "deceaseChance": 0,
      "deceaseEffects": [
        "falloutmc:example_effect"
      ],
      "effects": [
        {
          "duration": 0,
          "effect": "falloutmc:example_effect"
        }
      ],
      "hpRestore": 0,
      "hungerRestore": 4,
      "plantable": false,
      "radiation": 25,
      "recipe": false,
      "thirstRestore": 1,
      "value": 1,
      "weight": 0.2
    },
    "minecraft:porkchop": {
      "addiction": false,
      "deceaseChance": 0,
      "deceaseEffects": [
        "falloutmc:example_effect"
      ],
      "effects": [
        {
          "duration": 0,
          "effect": "falloutmc:example_effect"
        }
      ],
      "hpRestore": 4,
      "hungerRestore": 9,
      "plantable": false,
      "radiation": 12,
      "recipe": false,
      "thirstRestore": 2,
      "value": 7,
      "weight": 0.6
    },
    "minecraft:potato": {
      "addiction": false,
      "deceaseChance": 0,
      "deceaseEffects": [
        "falloutmc:example_effect"
      ],
      "effects": [
        {
          "duration": 0,
          "effect": "falloutmc:example_effect"
        }
      ],
      "hpRestore": 4,
      "hungerRestore": 11,
      "plantable": false,
      "radiation": 10,
      "recipe": false,
      "thirstRestore": 0,
      "value": 4,
      "weight": 0.3
    },
    "minecraft:potion": {
      "addiction": false,
      "deceaseChance": 0,
      "deceaseEffects": [
        "falloutmc:example_effect"
      ],
      "effects": [
        {
          "duration": 0,
          "effect": "falloutmc:example_effect"
        }
      ],
      "hpRestore": 0,
      "hungerRestore": 0,
      "plantable": false,
      "radiation": 20,
      "recipe": false,
      "thirstRestore": 12,
      "value": 0,
      "weight": 1.0
    },
    "minecraft:pufferfish": {
      "addiction": false,
      "deceaseChance": 0,
      "deceaseEffects": [
        "falloutmc:example_effect"
      ],
      "effects": [
        {
          "duration": 0,
          "effect": "falloutmc:example_effect"
        }
      ],
      "hpRestore": 1,
      "hungerRestore": 3,
      "plantable": false,
      "radiation": 12,
      "recipe": false,
      "thirstRestore": 10,
      "value": 4,
      "weight": 0.5
    },
    "minecraft:pumpkin_pie": {
      "addiction": false,
      "deceaseChance": 0,
      "deceaseEffects": [
        "falloutmc:example_effect"
      ],
      "effects": [
        {
          "duration": 0,
          "effect": "falloutmc:example_effect"
        }
      ],
      "hpRestore": 7,
      "hungerRestore": 15,
      "plantable": false,
      "radiation": 6,
      "recipe": false,
      "thirstRestore": 1,
      "value": 15,
      "weight": 0.7
    },
    "minecraft:rabbit": {
      "addiction": false,
      "deceaseChance": 0,
      "deceaseEffects": [
        "falloutmc:example_effect"
      ],
      "effects": [
        {
          "duration": 0,
          "effect": "falloutmc:example_effect"
        }
      ],
      "hpRestore": 3,
      "hungerRestore": 8,
      "plantable": false,
      "radiation": 9,
      "recipe": false,
      "thirstRestore": 1,
      "value": 0,
      "weight": 0.5
    },
    "minecraft:rotten_flesh": {
      "addiction": false,
      "deceaseChance": 0,
      "deceaseEffects": [
        "falloutmc:example_effect"
      ],
      "effects": [
        {
          "duration": 0,
          "effect": "falloutmc:example_effect"
        }
      ],
      "hpRestore": 1,
      "hungerRestore": 5,
      "plantable": false,
      "radiation": 35,
      "recipe": false,
      "thirstRestore": 0,
      "value": 1,
      "weight": 0.5
    },
    "minecraft:salmon": {
      "addiction": false,
      "deceaseChance": 0,
      "deceaseEffects": [
        "falloutmc:example_effect"
      ],
      "effects": [
        {
          "duration": 0,
          "effect": "falloutmc:example_effect"
        }
      ],
      "hpRestore": 4,
      "hungerRestore": 6,
      "plantable": false,
      "radiation": 4,
      "recipe": false,
      "thirstRestore": 3,
      "value": 5,
      "weight": 0.5
    },
    "minecraft:spider_eye": {
      "addiction": false,
      "deceaseChance": 0,
      "deceaseEffects": [
        "falloutmc:example_effect"
      ],
      "effects": [
        {
          "duration": 0,
          "effect": "falloutmc:example_effect"
        }
      ],
      "hpRestore": 1,
      "hungerRestore": 7,
      "plantable": false,
      "radiation": 15,
      "recipe": false,
      "thirstRestore": 2,
      "value": 3,
      "weight": 0.25
    },
    "minecraft:splash_potion": {
      "addiction": false,
      "deceaseChance": 0,
      "deceaseEffects": [
        "falloutmc:example_effect"
      ],
      "effects": [
        {
          "duration": 0,
          "effect": "falloutmc:example_effect"
        }
      ],
      "hpRestore": 0,
      "hungerRestore": 0,
      "plantable": false,
      "radiation": 20,
      "recipe": false,
      "thirstRestore": 12,
      "value": 0,
      "weight": 1.0
    },
    "minecraft:sweet_berries": {
      "addiction": false,
      "deceaseChance": 0,
      "deceaseEffects": [
        "falloutmc:example_effect"
      ],
      "effects": [
        {
          "duration": 0,
          "effect": "falloutmc:example_effect"
        }
      ],
      "hpRestore": 3,
      "hungerRestore": 5,
      "plantable": false,
      "radiation": 9,
      "recipe": false,
      "thirstRestore": 3,
      "value": 4,
      "weight": 0.2
    },
    "minecraft:tropical_fish": {
      "addiction": false,
      "deceaseChance": 0,
      "deceaseEffects": [
        "falloutmc:example_effect"
      ],
      "effects": [
        {
          "duration": 0,
          "effect": "falloutmc:example_effect"
        }
      ],
      "hpRestore": 4,
      "hungerRestore": 7,
      "plantable": false,
      "radiation": 13,
      "recipe": false,
      "thirstRestore": 6,
      "value": 6,
      "weight": 0.3
    },
    "minecraft:wheat": {
      "addiction": false,
      "deceaseChance": 0,
      "deceaseEffects": [
        "falloutmc:example_effect"
      ],
      "effects": [
        {
          "duration": 0,
          "effect": "falloutmc:example_effect"
        }
      ],
      "hpRestore": 2,
      "hungerRestore": 2,
      "plantable": false,
      "radiation": 14,
      "recipe": false,
      "thirstRestore": 0,
      "value": 1,
      "weight": 0.25
    }
  }
}